{
  "schema_name": "DoclingDocument",
  "version": "1.0.0",
  "name": "AGUA FEV",
  "origin": {
    "mimetype": "application/pdf",
    "binary_hash": 353370197348085946,
    "filename": "AGUA FEV.pdf"
  },
  "furniture": {
    "self_ref": "#/furniture",
    "children": [],
    "name": "_root_",
    "label": "unspecified"
  },
  "body": {
    "self_ref": "#/body",
    "children": [
      {
        "$ref": "#/pictures/0"
      },
      {
        "$ref": "#/pictures/1"
      },
      {
        "$ref": "#/pictures/2"
      },
      {
        "$ref": "#/groups/0"
      },
      {
        "$ref": "#/texts/83"
      },
      {
        "$ref": "#/texts/84"
      },
      {
        "$ref": "#/texts/85"
      },
      {
        "$ref": "#/texts/86"
      },
      {
        "$ref": "#/texts/87"
      },
      {
        "$ref": "#/pictures/3"
      }
    ],
    "name": "_root_",
    "label": "unspecified"
  },
  "groups": [
    {
      "self_ref": "#/groups/0",
      "parent": {
        "$ref": "#/body"
      },
      "children": [
        {
          "$ref": "#/texts/2"
        },
        {
          "$ref": "#/texts/3"
        },
        {
          "$ref": "#/texts/4"
        },
        {
          "$ref": "#/texts/5"
        },
        {
          "$ref": "#/texts/6"
        },
        {
          "$ref": "#/texts/7"
        },
        {
          "$ref": "#/texts/8"
        },
        {
          "$ref": "#/texts/9"
        },
        {
          "$ref": "#/texts/10"
        },
        {
          "$ref": "#/texts/11"
        },
        {
          "$ref": "#/texts/12"
        },
        {
          "$ref": "#/texts/13"
        },
        {
          "$ref": "#/texts/14"
        },
        {
          "$ref": "#/texts/15"
        },
        {
          "$ref": "#/texts/16"
        },
        {
          "$ref": "#/texts/17"
        },
        {
          "$ref": "#/texts/18"
        },
        {
          "$ref": "#/texts/19"
        },
        {
          "$ref": "#/texts/20"
        },
        {
          "$ref": "#/texts/21"
        },
        {
          "$ref": "#/texts/22"
        },
        {
          "$ref": "#/texts/23"
        },
        {
          "$ref": "#/texts/24"
        },
        {
          "$ref": "#/texts/25"
        },
        {
          "$ref": "#/texts/26"
        },
        {
          "$ref": "#/texts/27"
        },
        {
          "$ref": "#/texts/28"
        },
        {
          "$ref": "#/texts/29"
        },
        {
          "$ref": "#/texts/30"
        },
        {
          "$ref": "#/texts/31"
        },
        {
          "$ref": "#/texts/32"
        },
        {
          "$ref": "#/texts/33"
        },
        {
          "$ref": "#/texts/34"
        },
        {
          "$ref": "#/texts/35"
        },
        {
          "$ref": "#/texts/36"
        },
        {
          "$ref": "#/texts/37"
        },
        {
          "$ref": "#/texts/38"
        },
        {
          "$ref": "#/texts/39"
        },
        {
          "$ref": "#/texts/40"
        },
        {
          "$ref": "#/texts/41"
        },
        {
          "$ref": "#/texts/42"
        },
        {
          "$ref": "#/texts/43"
        },
        {
          "$ref": "#/texts/44"
        },
        {
          "$ref": "#/texts/45"
        },
        {
          "$ref": "#/texts/46"
        },
        {
          "$ref": "#/texts/47"
        },
        {
          "$ref": "#/texts/48"
        },
        {
          "$ref": "#/texts/49"
        },
        {
          "$ref": "#/texts/50"
        },
        {
          "$ref": "#/texts/51"
        },
        {
          "$ref": "#/texts/52"
        },
        {
          "$ref": "#/texts/53"
        },
        {
          "$ref": "#/texts/54"
        },
        {
          "$ref": "#/texts/55"
        },
        {
          "$ref": "#/texts/56"
        },
        {
          "$ref": "#/texts/57"
        },
        {
          "$ref": "#/texts/58"
        },
        {
          "$ref": "#/texts/59"
        },
        {
          "$ref": "#/texts/60"
        },
        {
          "$ref": "#/texts/61"
        },
        {
          "$ref": "#/texts/62"
        },
        {
          "$ref": "#/texts/63"
        },
        {
          "$ref": "#/texts/64"
        },
        {
          "$ref": "#/texts/65"
        },
        {
          "$ref": "#/texts/66"
        },
        {
          "$ref": "#/texts/67"
        },
        {
          "$ref": "#/texts/68"
        },
        {
          "$ref": "#/texts/69"
        },
        {
          "$ref": "#/texts/70"
        },
        {
          "$ref": "#/texts/71"
        },
        {
          "$ref": "#/texts/72"
        },
        {
          "$ref": "#/texts/73"
        },
        {
          "$ref": "#/texts/74"
        },
        {
          "$ref": "#/texts/75"
        },
        {
          "$ref": "#/texts/76"
        },
        {
          "$ref": "#/texts/77"
        },
        {
          "$ref": "#/texts/78"
        },
        {
          "$ref": "#/texts/79"
        },
        {
          "$ref": "#/texts/80"
        },
        {
          "$ref": "#/texts/81"
        },
        {
          "$ref": "#/texts/82"
        }
      ],
      "name": "group",
      "label": "form_area"
    }
  ],
  "texts": [
    {
      "self_ref": "#/texts/0",
      "parent": {
        "$ref": "#/pictures/0"
      },
      "children": [],
      "label": "text",
      "prov": [
        {
          "page_no": 1,
          "bbox": {
            "l": 15.0,
            "t": 806.3333333333334,
            "r": 147.66666666666666,
            "b": 801.0,
            "coord_origin": "BOTTOMLEFT"
          },
          "charspan": [
            0,
            65
          ]
        }
      ],
      "orig": "SEDE: Rua Campo do Brito, 331, 13 de Julho, Aracaju-SE, 49020-380",
      "text": "SEDE: Rua Campo do Brito, 331, 13 de Julho, Aracaju-SE, 49020-380"
    },
    {
      "self_ref": "#/texts/1",
      "parent": {
        "$ref": "#/pictures/2"
      },
      "children": [],
      "label": "text",
      "prov": [
        {
          "page_no": 1,
          "bbox": {
            "l": 44.333333333333336,
            "t": 259.0,
            "r": 143.0,
            "b": 252.33333333333337,
            "coord_origin": "BOTTOMLEFT"
          },
          "charspan": [
            0,
            34
          ]
        }
      ],
      "orig": "COMPANHIA DE SANEAMENTO DE SERGIPE",
      "text": "COMPANHIA DE SANEAMENTO DE SERGIPE"
    },
    {
      "self_ref": "#/texts/2",
      "parent": {
        "$ref": "#/groups/0"
      },
      "children": [],
      "label": "text",
      "prov": [
        {
          "page_no": 1,
          "bbox": {
            "l": 165.75,
            "t": 271.375,
            "r": 204.392,
            "b": 267.086,
            "coord_origin": "BOTTOMLEFT"
          },
          "charspan": [
            0,
            10
          ]
        }
      ],
      "orig": "0005036852",
      "text": "0005036852"
    },
    {
      "self_ref": "#/texts/3",
      "parent": {
        "$ref": "#/groups/0"
      },
      "children": [],
      "label": "text",
      "prov": [
        {
          "page_no": 1,
          "bbox": {
            "l": 285.75,
            "t": 797.25,
            "r": 299.95,
            "b": 793.918,
            "coord_origin": "BOTTOMLEFT"
          },
          "charspan": [
            0,
            6
          ]
        }
      ],
      "orig": "2ª Via",
      "text": "2ª Via"
    },
    {
      "self_ref": "#/texts/4",
      "parent": {
        "$ref": "#/groups/0"
      },
      "children": [],
      "label": "text",
      "prov": [
        {
          "page_no": 1,
          "bbox": {
            "l": 15.25,
            "t": 703.625,
            "r": 63.719,
            "b": 700.879,
            "coord_origin": "BOTTOMLEFT"
          },
          "charspan": [
            0,
            21
          ]
        }
      ],
      "orig": "Consumo Faturado (m3)",
      "text": "Consumo Faturado (m3)"
    },
    {
      "self_ref": "#/texts/5",
      "parent": {
        "$ref": "#/groups/0"
      },
      "children": [],
      "label": "text",
      "prov": [
        {
          "page_no": 1,
          "bbox": {
            "l": 15.0,
            "t": 806.3333333333334,
            "r": 147.66666666666666,
            "b": 801.0,
            "coord_origin": "BOTTOMLEFT"
          },
          "charspan": [
            0,
            65
          ]
        }
      ],
      "orig": "SEDE: Rua Campo do Brito, 331, 13 de Julho, Aracaju-SE, 49020-380",
      "text": "SEDE: Rua Campo do Brito, 331, 13 de Julho, Aracaju-SE, 49020-380"
    },
    {
      "self_ref": "#/texts/6",
      "parent": {
        "$ref": "#/groups/0"
      },
      "children": [],
      "label": "text",
      "prov": [
        {
          "page_no": 1,
          "bbox": {
            "l": 15.25,
            "t": 695.425,
            "r": 58.02799999999999,
            "b": 692.679,
            "coord_origin": "BOTTOMLEFT"
          },
          "charspan": [
            0,
            18
          ]
        }
      ],
      "orig": "Media Consumo (m3)",
      "text": "Media Consumo (m3)"
    },
    {
      "self_ref": "#/texts/7",
      "parent": {
        "$ref": "#/groups/0"
      },
      "children": [],
      "label": "text",
      "prov": [
        {
          "page_no": 1,
          "bbox": {
            "l": 15.25,
            "t": 711.425,
            "r": 35.039,
            "b": 708.679,
            "coord_origin": "BOTTOMLEFT"
          },
          "charspan": [
            0,
            11
          ]
        }
      ],
      "orig": "Leit. Atual",
      "text": "Leit. Atual"
    },
    {
      "self_ref": "#/texts/8",
      "parent": {
        "$ref": "#/groups/0"
      },
      "children": [],
      "label": "text",
      "prov": [
        {
          "page_no": 1,
          "bbox": {
            "l": 121.19999999999999,
            "t": 446.94999999999993,
            "r": 160.102,
            "b": 443.61799999999994,
            "coord_origin": "BOTTOMLEFT"
          },
          "charspan": [
            0,
            11
          ]
        }
      ],
      "orig": "VENCIMENTO:",
      "text": "VENCIMENTO:"
    },
    {
      "self_ref": "#/texts/9",
      "parent": {
        "$ref": "#/groups/0"
      },
      "children": [],
      "label": "text",
      "prov": [
        {
          "page_no": 1,
          "bbox": {
            "l": 15.25,
            "t": 719.825,
            "r": 40.477,
            "b": 717.079,
            "coord_origin": "BOTTOMLEFT"
          },
          "charspan": [
            0,
            14
          ]
        }
      ],
      "orig": "Leit. Anterior",
      "text": "Leit. Anterior"
    },
    {
      "self_ref": "#/texts/10",
      "parent": {
        "$ref": "#/groups/0"
      },
      "children": [],
      "label": "text",
      "prov": [
        {
          "page_no": 1,
          "bbox": {
            "l": 15.25,
            "t": 686.425,
            "r": 57.298,
            "b": 683.679,
            "coord_origin": "BOTTOMLEFT"
          },
          "charspan": [
            0,
            22
          ]
        }
      ],
      "orig": "Data de Leit. Anterior",
      "text": "Data de Leit. Anterior"
    },
    {
      "self_ref": "#/texts/11",
      "parent": {
        "$ref": "#/groups/0"
      },
      "children": [],
      "label": "text",
      "prov": [
        {
          "page_no": 1,
          "bbox": {
            "l": 15.25,
            "t": 668.4750000000001,
            "r": 62.736,
            "b": 665.7290000000002,
            "coord_origin": "BOTTOMLEFT"
          },
          "charspan": [
            0,
            24
          ]
        }
      ],
      "orig": "Previsão para Prox. Leit",
      "text": "Previsão para Prox. Leit"
    },
    {
      "self_ref": "#/texts/12",
      "parent": {
        "$ref": "#/groups/0"
      },
      "children": [],
      "label": "text",
      "prov": [
        {
          "page_no": 1,
          "bbox": {
            "l": 14.550000000000002,
            "t": 591.9,
            "r": 35.254,
            "b": 588.568,
            "coord_origin": "BOTTOMLEFT"
          },
          "charspan": [
            0,
            8
          ]
        }
      ],
      "orig": "Serviços",
      "text": "Serviços"
    },
    {
      "self_ref": "#/texts/13",
      "parent": {
        "$ref": "#/groups/0"
      },
      "children": [],
      "label": "text",
      "prov": [
        {
          "page_no": 1,
          "bbox": {
            "l": 249.66666666666666,
            "t": 793.0,
            "r": 259.6666666666667,
            "b": 788.3333333333334,
            "coord_origin": "BOTTOMLEFT"
          },
          "charspan": [
            0,
            4
          ]
        }
      ],
      "orig": "CPF;",
      "text": "CPF;"
    },
    {
      "self_ref": "#/texts/14",
      "parent": {
        "$ref": "#/groups/0"
      },
      "children": [],
      "label": "text",
      "prov": [
        {
          "page_no": 1,
          "bbox": {
            "l": 275.55,
            "t": 594.85,
            "r": 287.754,
            "b": 591.518,
            "coord_origin": "BOTTOMLEFT"
          },
          "charspan": [
            0,
            5
          ]
        }
      ],
      "orig": "Valor",
      "text": "Valor"
    },
    {
      "self_ref": "#/texts/15",
      "parent": {
        "$ref": "#/groups/0"
      },
      "children": [],
      "label": "text",
      "prov": [
        {
          "page_no": 1,
          "bbox": {
            "l": 15.25,
            "t": 627.575,
            "r": 58.032,
            "b": 624.829,
            "coord_origin": "BOTTOMLEFT"
          },
          "charspan": [
            0,
            20
          ]
        }
      ],
      "orig": "Histórico de consumo",
      "text": "Histórico de consumo"
    },
    {
      "self_ref": "#/texts/16",
      "parent": {
        "$ref": "#/groups/0"
      },
      "children": [],
      "label": "text",
      "prov": [
        {
          "page_no": 1,
          "bbox": {
            "l": 13.0,
            "t": 771.6666666666666,
            "r": 31.0,
            "b": 767.0,
            "coord_origin": "BOTTOMLEFT"
          },
          "charspan": [
            0,
            8
          ]
        }
      ],
      "orig": "Endereço",
      "text": "Endereço"
    },
    {
      "self_ref": "#/texts/17",
      "parent": {
        "$ref": "#/groups/0"
      },
      "children": [],
      "label": "text",
      "prov": [
        {
          "page_no": 1,
          "bbox": {
            "l": 249.80000000000004,
            "t": 736.75,
            "r": 300.799,
            "b": 735.145,
            "coord_origin": "BOTTOMLEFT"
          },
          "charspan": [
            0,
            34
          ]
        }
      ],
      "orig": "ECO RES  ECO COM  ECO IND  ECO PUB",
      "text": "ECO RES  ECO COM  ECO IND  ECO PUB"
    },
    {
      "self_ref": "#/texts/18",
      "parent": {
        "$ref": "#/groups/0"
      },
      "children": [],
      "label": "text",
      "prov": [
        {
          "page_no": 1,
          "bbox": {
            "l": 15.25,
            "t": 676.825,
            "r": 49.626,
            "b": 674.079,
            "coord_origin": "BOTTOMLEFT"
          },
          "charspan": [
            0,
            15
          ]
        }
      ],
      "orig": "Dias de consumo",
      "text": "Dias de consumo"
    },
    {
      "self_ref": "#/texts/19",
      "parent": {
        "$ref": "#/groups/0"
      },
      "children": [],
      "label": "text",
      "prov": [
        {
          "page_no": 1,
          "bbox": {
            "l": 15.25,
            "t": 644.875,
            "r": 73.861,
            "b": 642.129,
            "coord_origin": "BOTTOMLEFT"
          },
          "charspan": [
            0,
            26
          ]
        }
      ],
      "orig": "Informações complementares",
      "text": "Informações complementares"
    },
    {
      "self_ref": "#/texts/20",
      "parent": {
        "$ref": "#/groups/0"
      },
      "children": [],
      "label": "text",
      "prov": [
        {
          "page_no": 1,
          "bbox": {
            "l": 15.25,
            "t": 636.7250000000001,
            "r": 60.76,
            "b": 633.9790000000002,
            "coord_origin": "BOTTOMLEFT"
          },
          "charspan": [
            0,
            21
          ]
        }
      ],
      "orig": "Código do responsável",
      "text": "Código do responsável"
    },
    {
      "self_ref": "#/texts/21",
      "parent": {
        "$ref": "#/groups/0"
      },
      "children": [],
      "label": "text",
      "prov": [
        {
          "page_no": 1,
          "bbox": {
            "l": 15.25,
            "t": 652.825,
            "r": 56.54999999999999,
            "b": 650.079,
            "coord_origin": "BOTTOMLEFT"
          },
          "charspan": [
            0,
            21
          ]
        }
      ],
      "orig": "Ocorrência de leitura",
      "text": "Ocorrência de leitura"
    },
    {
      "self_ref": "#/texts/22",
      "parent": {
        "$ref": "#/groups/0"
      },
      "children": [],
      "label": "section_header",
      "prov": [
        {
          "page_no": 1,
          "bbox": {
            "l": 184.45,
            "t": 814.175,
            "r": 236.00200000000004,
            "b": 808.652,
            "coord_origin": "BOTTOMLEFT"
          },
          "charspan": [
            0,
            11
          ]
        }
      ],
      "orig": "119.308.555",
      "text": "119.308.555",
      "level": 1
    },
    {
      "self_ref": "#/texts/23",
      "parent": {
        "$ref": "#/groups/0"
      },
      "children": [],
      "label": "section_header",
      "prov": [
        {
          "page_no": 1,
          "bbox": {
            "l": 14.199999999999998,
            "t": 780.7749999999999,
            "r": 88.306,
            "b": 775.2520000000001,
            "coord_origin": "BOTTOMLEFT"
          },
          "charspan": [
            0,
            14
          ]
        }
      ],
      "orig": "SIMONI POSSARI",
      "text": "SIMONI POSSARI",
      "level": 1
    },
    {
      "self_ref": "#/texts/24",
      "parent": {
        "$ref": "#/groups/0"
      },
      "children": [],
      "label": "text",
      "prov": [
        {
          "page_no": 1,
          "bbox": {
            "l": 14.199999999999998,
            "t": 762.7250000000001,
            "r": 248.32499999999996,
            "b": 758.868,
            "coord_origin": "BOTTOMLEFT"
          },
          "charspan": [
            0,
            69
          ]
        }
      ],
      "orig": "RUA MARIZE ALMEIDA SANTOS 521 - LUZIA - ARACAJU - -ARACAJU - 49045500",
      "text": "RUA MARIZE ALMEIDA SANTOS 521 - LUZIA - ARACAJU - -ARACAJU - 49045500"
    },
    {
      "self_ref": "#/texts/25",
      "parent": {
        "$ref": "#/groups/0"
      },
      "children": [],
      "label": "text",
      "prov": [
        {
          "page_no": 1,
          "bbox": {
            "l": 14.199999999999998,
            "t": 750.175,
            "r": 54.394,
            "b": 746.3179999999999,
            "coord_origin": "BOTTOMLEFT"
          },
          "charspan": [
            0,
            12
          ]
        }
      ],
      "orig": "EDF S AP 101",
      "text": "EDF S AP 101"
    },
    {
      "self_ref": "#/texts/26",
      "parent": {
        "$ref": "#/groups/0"
      },
      "children": [],
      "label": "text",
      "prov": [
        {
          "page_no": 1,
          "bbox": {
            "l": 93.66666666666667,
            "t": 743.6666666666666,
            "r": 121.0,
            "b": 739.0,
            "coord_origin": "BOTTOMLEFT"
          },
          "charspan": [
            0,
            15
          ]
        }
      ],
      "orig": "Dala da Leitura",
      "text": "Dala da Leitura"
    },
    {
      "self_ref": "#/texts/27",
      "parent": {
        "$ref": "#/groups/0"
      },
      "children": [],
      "label": "text",
      "prov": [
        {
          "page_no": 1,
          "bbox": {
            "l": 179.66666666666666,
            "t": 743.6666666666666,
            "r": 200.33333333333334,
            "b": 739.0,
            "coord_origin": "BOTTOMLEFT"
          },
          "charspan": [
            0,
            10
          ]
        }
      ],
      "orig": "Hidrómetro",
      "text": "Hidrómetro"
    },
    {
      "self_ref": "#/texts/28",
      "parent": {
        "$ref": "#/groups/0"
      },
      "children": [],
      "label": "text",
      "prov": [
        {
          "page_no": 1,
          "bbox": {
            "l": 180.65,
            "t": 730.9750000000001,
            "r": 222.385,
            "b": 726.563,
            "coord_origin": "BOTTOMLEFT"
          },
          "charspan": [
            0,
            10
          ]
        }
      ],
      "orig": "A07N537222",
      "text": "A07N537222"
    },
    {
      "self_ref": "#/texts/29",
      "parent": {
        "$ref": "#/groups/0"
      },
      "children": [],
      "label": "text",
      "prov": [
        {
          "page_no": 1,
          "bbox": {
            "l": 249.66666666666666,
            "t": 743.6666666666666,
            "r": 295.6666666666667,
            "b": 739.0,
            "coord_origin": "BOTTOMLEFT"
          },
          "charspan": [
            0,
            23
          ]
        }
      ],
      "orig": "Classificaçao Economias",
      "text": "Classificaçao Economias"
    },
    {
      "self_ref": "#/texts/30",
      "parent": {
        "$ref": "#/groups/0"
      },
      "children": [],
      "label": "section_header",
      "prov": [
        {
          "page_no": 1,
          "bbox": {
            "l": 98.6,
            "t": 731.375,
            "r": 183.195,
            "b": 725.852,
            "coord_origin": "BOTTOMLEFT"
          },
          "charspan": [
            0,
            20
          ]
        }
      ],
      "orig": "05/02/2024  13:55:02",
      "text": "05/02/2024  13:55:02",
      "level": 1
    },
    {
      "self_ref": "#/texts/31",
      "parent": {
        "$ref": "#/groups/0"
      },
      "children": [],
      "label": "text",
      "prov": [
        {
          "page_no": 1,
          "bbox": {
            "l": 168.95,
            "t": 448.32499999999993,
            "r": 236.53200000000004,
            "b": 443.91299999999995,
            "coord_origin": "BOTTOMLEFT"
          },
          "charspan": [
            0,
            20
          ]
        }
      ],
      "orig": "15/02/2024  00:00:00",
      "text": "15/02/2024  00:00:00"
    },
    {
      "self_ref": "#/texts/32",
      "parent": {
        "$ref": "#/groups/0"
      },
      "children": [],
      "label": "text",
      "prov": [
        {
          "page_no": 1,
          "bbox": {
            "l": 46.4,
            "t": 447.225,
            "r": 72.24,
            "b": 442.813,
            "coord_origin": "BOTTOMLEFT"
          },
          "charspan": [
            0,
            7
          ]
        }
      ],
      "orig": "02/2024",
      "text": "02/2024"
    },
    {
      "self_ref": "#/texts/33",
      "parent": {
        "$ref": "#/groups/0"
      },
      "children": [],
      "label": "text",
      "prov": [
        {
          "page_no": 1,
          "bbox": {
            "l": 259.2,
            "t": 270.875,
            "r": 321.402,
            "b": 265.352,
            "coord_origin": "BOTTOMLEFT"
          },
          "charspan": [
            0,
            15
          ]
        }
      ],
      "orig": "15/02/2024  00:",
      "text": "15/02/2024  00:"
    },
    {
      "self_ref": "#/texts/34",
      "parent": {
        "$ref": "#/groups/0"
      },
      "children": [],
      "label": "text",
      "prov": [
        {
          "page_no": 1,
          "bbox": {
            "l": 251.85000000000002,
            "t": 806.7250000000001,
            "r": 291.604,
            "b": 802.313,
            "coord_origin": "BOTTOMLEFT"
          },
          "charspan": [
            0,
            10
          ]
        }
      ],
      "orig": "0005036852",
      "text": "0005036852"
    },
    {
      "self_ref": "#/texts/35",
      "parent": {
        "$ref": "#/groups/0"
      },
      "children": [],
      "label": "section_header",
      "prov": [
        {
          "page_no": 1,
          "bbox": {
            "l": 70.05,
            "t": 393.17500000000007,
            "r": 244.044,
            "b": 389.318,
            "coord_origin": "BOTTOMLEFT"
          },
          "charspan": [
            0,
            49
          ]
        }
      ],
      "orig": "IDENTIFICADOR PARA DEBITO AUTOMATICO : 0005036852",
      "text": "IDENTIFICADOR PARA DEBITO AUTOMATICO : 0005036852",
      "level": 1
    },
    {
      "self_ref": "#/texts/36",
      "parent": {
        "$ref": "#/groups/0"
      },
      "children": [],
      "label": "text",
      "prov": [
        {
          "page_no": 1,
          "bbox": {
            "l": 18.95,
            "t": 434.82499999999993,
            "r": 168.959,
            "b": 432.63400000000007,
            "coord_origin": "BOTTOMLEFT"
          },
          "charspan": [
            0,
            74
          ]
        }
      ],
      "orig": "REAJUSTE TARIFARIO DE 4,04 POR CENTO, APROVADO ATRAVES DA PORTARIA N 11/20",
      "text": "REAJUSTE TARIFARIO DE 4,04 POR CENTO, APROVADO ATRAVES DA PORTARIA N 11/20"
    },
    {
      "self_ref": "#/texts/37",
      "parent": {
        "$ref": "#/groups/0"
      },
      "children": [],
      "label": "text",
      "prov": [
        {
          "page_no": 1,
          "bbox": {
            "l": 18.95,
            "t": 429.82499999999993,
            "r": 120.452,
            "b": 427.63400000000007,
            "coord_origin": "BOTTOMLEFT"
          },
          "charspan": [
            0,
            52
          ]
        }
      ],
      "orig": "DA AGRESE, DIVULGADA NO DIÁRIO OFICIAL DE 31/01/2024",
      "text": "DA AGRESE, DIVULGADA NO DIÁRIO OFICIAL DE 31/01/2024"
    },
    {
      "self_ref": "#/texts/38",
      "parent": {
        "$ref": "#/groups/0"
      },
      "children": [],
      "label": "text",
      "prov": [
        {
          "page_no": 1,
          "bbox": {
            "l": 18.95,
            "t": 424.525,
            "r": 108.40599999999999,
            "b": 422.334,
            "coord_origin": "BOTTOMLEFT"
          },
          "charspan": [
            0,
            46
          ]
        }
      ],
      "orig": "A SER APLICADA A PARTIR DA REFERENCIA 03/2024.",
      "text": "A SER APLICADA A PARTIR DA REFERENCIA 03/2024."
    },
    {
      "self_ref": "#/texts/39",
      "parent": {
        "$ref": "#/groups/0"
      },
      "children": [],
      "label": "text",
      "prov": [
        {
          "page_no": 1,
          "bbox": {
            "l": 252.35000000000002,
            "t": 731.05,
            "r": 254.518,
            "b": 729.445,
            "coord_origin": "BOTTOMLEFT"
          },
          "charspan": [
            0,
            1
          ]
        }
      ],
      "orig": "1",
      "text": "1"
    },
    {
      "self_ref": "#/texts/40",
      "parent": {
        "$ref": "#/groups/0"
      },
      "children": [],
      "label": "text",
      "prov": [
        {
          "page_no": 1,
          "bbox": {
            "l": 267.85,
            "t": 730.8,
            "r": 270.018,
            "b": 729.195,
            "coord_origin": "BOTTOMLEFT"
          },
          "charspan": [
            0,
            1
          ]
        }
      ],
      "orig": "0",
      "text": "0"
    },
    {
      "self_ref": "#/texts/41",
      "parent": {
        "$ref": "#/groups/0"
      },
      "children": [],
      "label": "text",
      "prov": [
        {
          "page_no": 1,
          "bbox": {
            "l": 281.15,
            "t": 731.0,
            "r": 283.318,
            "b": 729.395,
            "coord_origin": "BOTTOMLEFT"
          },
          "charspan": [
            0,
            1
          ]
        }
      ],
      "orig": "0",
      "text": "0"
    },
    {
      "self_ref": "#/texts/42",
      "parent": {
        "$ref": "#/groups/0"
      },
      "children": [],
      "label": "text",
      "prov": [
        {
          "page_no": 1,
          "bbox": {
            "l": 294.95,
            "t": 731.45,
            "r": 297.118,
            "b": 729.845,
            "coord_origin": "BOTTOMLEFT"
          },
          "charspan": [
            0,
            1
          ]
        }
      ],
      "orig": "0",
      "text": "0"
    },
    {
      "self_ref": "#/texts/43",
      "parent": {
        "$ref": "#/groups/0"
      },
      "children": [],
      "label": "text",
      "prov": [
        {
          "page_no": 1,
          "bbox": {
            "l": 119.30000000000001,
            "t": 702.7749999999999,
            "r": 125.485,
            "b": 700.0289999999999,
            "coord_origin": "BOTTOMLEFT"
          },
          "charspan": [
            0,
            2
          ]
        }
      ],
      "orig": "17",
      "text": "17"
    },
    {
      "self_ref": "#/texts/44",
      "parent": {
        "$ref": "#/groups/0"
      },
      "children": [],
      "label": "text",
      "prov": [
        {
          "page_no": 1,
          "bbox": {
            "l": 110.5,
            "t": 685.175,
            "r": 152.561,
            "b": 682.429,
            "coord_origin": "BOTTOMLEFT"
          },
          "charspan": [
            0,
            20
          ]
        }
      ],
      "orig": "05/01/2024  13:40:27",
      "text": "05/01/2024  13:40:27"
    },
    {
      "self_ref": "#/texts/45",
      "parent": {
        "$ref": "#/groups/0"
      },
      "children": [],
      "label": "text",
      "prov": [
        {
          "page_no": 1,
          "bbox": {
            "l": 111.94999999999999,
            "t": 636.925,
            "r": 132.981,
            "b": 634.179,
            "coord_origin": "BOTTOMLEFT"
          },
          "charspan": [
            0,
            9
          ]
        }
      ],
      "orig": "5.036.852",
      "text": "5.036.852"
    },
    {
      "self_ref": "#/texts/46",
      "parent": {
        "$ref": "#/groups/0"
      },
      "children": [],
      "label": "text",
      "prov": [
        {
          "page_no": 1,
          "bbox": {
            "l": 110.59999999999998,
            "t": 668.175,
            "r": 152.661,
            "b": 665.429,
            "coord_origin": "BOTTOMLEFT"
          },
          "charspan": [
            0,
            20
          ]
        }
      ],
      "orig": "06/03/2024  13:55:02",
      "text": "06/03/2024  13:55:02"
    },
    {
      "self_ref": "#/texts/47",
      "parent": {
        "$ref": "#/groups/0"
      },
      "children": [],
      "label": "text",
      "prov": [
        {
          "page_no": 1,
          "bbox": {
            "l": 15.149999999999999,
            "t": 620.325,
            "r": 163.363,
            "b": 618.134,
            "coord_origin": "BOTTOMLEFT"
          },
          "charspan": [
            0,
            98
          ]
        }
      ],
      "orig": "JAN/2024       00021      OUT/2023       00012      JUL/2023       00012      ABR/2023       00010",
      "text": "JAN/2024       00021      OUT/2023       00012      JUL/2023       00012      ABR/2023       00010"
    },
    {
      "self_ref": "#/texts/48",
      "parent": {
        "$ref": "#/groups/0"
      },
      "children": [],
      "label": "text",
      "prov": [
        {
          "page_no": 1,
          "bbox": {
            "l": 15.25,
            "t": 613.625,
            "r": 164.446,
            "b": 611.434,
            "coord_origin": "BOTTOMLEFT"
          },
          "charspan": [
            0,
            98
          ]
        }
      ],
      "orig": "DEZ/2023       00017      SET/2023       00013      JUN/2023       00012      MAR/2023       00015",
      "text": "DEZ/2023       00017      SET/2023       00013      JUN/2023       00012      MAR/2023       00015"
    },
    {
      "self_ref": "#/texts/49",
      "parent": {
        "$ref": "#/groups/0"
      },
      "children": [],
      "label": "text",
      "prov": [
        {
          "page_no": 1,
          "bbox": {
            "l": 116.25,
            "t": 695.075,
            "r": 128.621,
            "b": 692.329,
            "coord_origin": "BOTTOMLEFT"
          },
          "charspan": [
            0,
            5
          ]
        }
      ],
      "orig": "16,00",
      "text": "16,00"
    },
    {
      "self_ref": "#/texts/50",
      "parent": {
        "$ref": "#/groups/0"
      },
      "children": [],
      "label": "text",
      "prov": [
        {
          "page_no": 1,
          "bbox": {
            "l": 15.25,
            "t": 607.025,
            "r": 164.204,
            "b": 604.834,
            "coord_origin": "BOTTOMLEFT"
          },
          "charspan": [
            0,
            98
          ]
        }
      ],
      "orig": "NOV/2023       00015      AGO/2023       00012      MAI/2023       00011      FEV/2023       00021",
      "text": "NOV/2023       00015      AGO/2023       00012      MAI/2023       00011      FEV/2023       00021"
    },
    {
      "self_ref": "#/texts/51",
      "parent": {
        "$ref": "#/groups/0"
      },
      "children": [],
      "label": "text",
      "prov": [
        {
          "page_no": 1,
          "bbox": {
            "l": 116.25,
            "t": 711.4750000000001,
            "r": 128.621,
            "b": 708.7290000000002,
            "coord_origin": "BOTTOMLEFT"
          },
          "charspan": [
            0,
            5
          ]
        }
      ],
      "orig": "2.544",
      "text": "2.544"
    },
    {
      "self_ref": "#/texts/52",
      "parent": {
        "$ref": "#/groups/0"
      },
      "children": [],
      "label": "text",
      "prov": [
        {
          "page_no": 1,
          "bbox": {
            "l": 116.25,
            "t": 719.4750000000001,
            "r": 128.621,
            "b": 716.7290000000002,
            "coord_origin": "BOTTOMLEFT"
          },
          "charspan": [
            0,
            5
          ]
        }
      ],
      "orig": "2.527",
      "text": "2.527"
    },
    {
      "self_ref": "#/texts/53",
      "parent": {
        "$ref": "#/groups/0"
      },
      "children": [],
      "label": "text",
      "prov": [
        {
          "page_no": 1,
          "bbox": {
            "l": 15.75,
            "t": 582.875,
            "r": 51.555,
            "b": 580.129,
            "coord_origin": "BOTTOMLEFT"
          },
          "charspan": [
            0,
            13
          ]
        }
      ],
      "orig": "VALOR DE AGUA",
      "text": "VALOR DE AGUA"
    },
    {
      "self_ref": "#/texts/54",
      "parent": {
        "$ref": "#/groups/0"
      },
      "children": [],
      "label": "text",
      "prov": [
        {
          "page_no": 1,
          "bbox": {
            "l": 15.75,
            "t": 574.775,
            "r": 58.185,
            "b": 572.029,
            "coord_origin": "BOTTOMLEFT"
          },
          "charspan": [
            0,
            15
          ]
        }
      ],
      "orig": "VALOR DE ESGOTO",
      "text": "VALOR DE ESGOTO"
    },
    {
      "self_ref": "#/texts/55",
      "parent": {
        "$ref": "#/groups/0"
      },
      "children": [],
      "label": "text",
      "prov": [
        {
          "page_no": 1,
          "bbox": {
            "l": 15.75,
            "t": 566.675,
            "r": 54.767999999999994,
            "b": 563.929,
            "coord_origin": "BOTTOMLEFT"
          },
          "charspan": [
            0,
            14
          ]
        }
      ],
      "orig": "VALOR DO JUROS",
      "text": "VALOR DO JUROS"
    },
    {
      "self_ref": "#/texts/56",
      "parent": {
        "$ref": "#/groups/0"
      },
      "children": [],
      "label": "text",
      "prov": [
        {
          "page_no": 1,
          "bbox": {
            "l": 279.85,
            "t": 583.675,
            "r": 294.397,
            "b": 564.429,
            "coord_origin": "BOTTOMLEFT"
          },
          "charspan": [
            0,
            17
          ]
        }
      ],
      "orig": "112,65 90,12 1,49",
      "text": "112,65 90,12 1,49"
    },
    {
      "self_ref": "#/texts/57",
      "parent": {
        "$ref": "#/groups/0"
      },
      "children": [],
      "label": "text",
      "prov": [
        {
          "page_no": 1,
          "bbox": {
            "l": 15.25,
            "t": 660.925,
            "r": 39.485,
            "b": 658.179,
            "coord_origin": "BOTTOMLEFT"
          },
          "charspan": [
            0,
            12
          ]
        }
      ],
      "orig": "Média diária",
      "text": "Média diária"
    },
    {
      "self_ref": "#/texts/58",
      "parent": {
        "$ref": "#/groups/0"
      },
      "children": [],
      "label": "text",
      "prov": [
        {
          "page_no": 1,
          "bbox": {
            "l": 117.44999999999999,
            "t": 660.375,
            "r": 127.347,
            "b": 657.629,
            "coord_origin": "BOTTOMLEFT"
          },
          "charspan": [
            0,
            4
          ]
        }
      ],
      "orig": "0,52",
      "text": "0,52"
    },
    {
      "self_ref": "#/texts/59",
      "parent": {
        "$ref": "#/groups/0"
      },
      "children": [],
      "label": "text",
      "prov": [
        {
          "page_no": 1,
          "bbox": {
            "l": 121.65000000000002,
            "t": 652.875,
            "r": 123.13199999999999,
            "b": 650.129,
            "coord_origin": "BOTTOMLEFT"
          },
          "charspan": [
            0,
            1
          ]
        }
      ],
      "orig": "-",
      "text": "-"
    },
    {
      "self_ref": "#/texts/60",
      "parent": {
        "$ref": "#/groups/0"
      },
      "children": [],
      "label": "text",
      "prov": [
        {
          "page_no": 1,
          "bbox": {
            "l": 279.15,
            "t": 448.17500000000007,
            "r": 309.007,
            "b": 442.652,
            "coord_origin": "BOTTOMLEFT"
          },
          "charspan": [
            0,
            6
          ]
        }
      ],
      "orig": "204,26",
      "text": "204,26"
    },
    {
      "self_ref": "#/texts/61",
      "parent": {
        "$ref": "#/groups/0"
      },
      "children": [],
      "label": "text",
      "prov": [
        {
          "page_no": 1,
          "bbox": {
            "l": 119.30000000000001,
            "t": 677.175,
            "r": 125.485,
            "b": 674.429,
            "coord_origin": "BOTTOMLEFT"
          },
          "charspan": [
            0,
            2
          ]
        }
      ],
      "orig": "31",
      "text": "31"
    },
    {
      "self_ref": "#/texts/62",
      "parent": {
        "$ref": "#/groups/0"
      },
      "children": [],
      "label": "text",
      "prov": [
        {
          "page_no": 1,
          "bbox": {
            "l": 16.333333333333332,
            "t": 455.6666666666667,
            "r": 47.0,
            "b": 451.0,
            "coord_origin": "BOTTOMLEFT"
          },
          "charspan": [
            0,
            15
          ]
        }
      ],
      "orig": "Mês Referència:",
      "text": "Mês Referència:"
    },
    {
      "self_ref": "#/texts/63",
      "parent": {
        "$ref": "#/groups/0"
      },
      "children": [],
      "label": "text",
      "prov": [
        {
          "page_no": 1,
          "bbox": {
            "l": 217.66666666666666,
            "t": 456.3333333333333,
            "r": 255.0,
            "b": 451.0,
            "coord_origin": "BOTTOMLEFT"
          },
          "charspan": [
            0,
            16
          ]
        }
      ],
      "orig": "TOTAL A PAGAR RS",
      "text": "TOTAL A PAGAR RS"
    },
    {
      "self_ref": "#/texts/64",
      "parent": {
        "$ref": "#/groups/0"
      },
      "children": [],
      "label": "section_header",
      "prov": [
        {
          "page_no": 1,
          "bbox": {
            "l": 59.0,
            "t": 372.3333333333333,
            "r": 262.3333333333333,
            "b": 359.0,
            "coord_origin": "BOTTOMLEFT"
          },
          "charspan": [
            0,
            102
          ]
        }
      ],
      "orig": "CANAIS DE ATENDIMENTO: 0800 079 0195 SAC: 4020-0195 AGÊNCIA VIRTUAL: WWW-deso-se-com brlagenciavirtual",
      "text": "CANAIS DE ATENDIMENTO: 0800 079 0195 SAC: 4020-0195 AGÊNCIA VIRTUAL: WWW-deso-se-com brlagenciavirtual",
      "level": 1
    },
    {
      "self_ref": "#/texts/65",
      "parent": {
        "$ref": "#/groups/0"
      },
      "children": [],
      "label": "text",
      "prov": [
        {
          "page_no": 1,
          "bbox": {
            "l": 26.666666666666668,
            "t": 358.6666666666667,
            "r": 239.66666666666666,
            "b": 350.0,
            "coord_origin": "BOTTOMLEFT"
          },
          "charspan": [
            0,
            60
          ]
        }
      ],
      "orig": "Qualidade da Água Distribuída (Decreto Federal n\" 5.440/2005",
      "text": "Qualidade da Água Distribuída (Decreto Federal n\" 5.440/2005"
    },
    {
      "self_ref": "#/texts/66",
      "parent": {
        "$ref": "#/groups/0"
      },
      "children": [],
      "label": "text",
      "prov": [
        {
          "page_no": 1,
          "bbox": {
            "l": 246.66666666666666,
            "t": 358.0,
            "r": 295.3333333333333,
            "b": 350.0,
            "coord_origin": "BOTTOMLEFT"
          },
          "charspan": [
            0,
            16
          ]
        }
      ],
      "orig": "Art.50 inciso /)",
      "text": "Art.50 inciso /)"
    },
    {
      "self_ref": "#/texts/67",
      "parent": {
        "$ref": "#/groups/0"
      },
      "children": [],
      "label": "text",
      "prov": [
        {
          "page_no": 1,
          "bbox": {
            "l": 122.66666666666667,
            "t": 347.6666666666667,
            "r": 143.66666666666666,
            "b": 341.0,
            "coord_origin": "BOTTOMLEFT"
          },
          "charspan": [
            0,
            8
          ]
        }
      ],
      "orig": "Turbidez",
      "text": "Turbidez"
    },
    {
      "self_ref": "#/texts/68",
      "parent": {
        "$ref": "#/groups/0"
      },
      "children": [],
      "label": "text",
      "prov": [
        {
          "page_no": 1,
          "bbox": {
            "l": 159.66666666666666,
            "t": 346.3333333333333,
            "r": 169.0,
            "b": 341.6666666666667,
            "coord_origin": "BOTTOMLEFT"
          },
          "charspan": [
            0,
            3
          ]
        }
      ],
      "orig": "Cor",
      "text": "Cor"
    },
    {
      "self_ref": "#/texts/69",
      "parent": {
        "$ref": "#/groups/0"
      },
      "children": [],
      "label": "text",
      "prov": [
        {
          "page_no": 1,
          "bbox": {
            "l": 183.66666666666666,
            "t": 346.3333333333333,
            "r": 197.0,
            "b": 341.6666666666667,
            "coord_origin": "BOTTOMLEFT"
          },
          "charspan": [
            0,
            5
          ]
        }
      ],
      "orig": "Cloro",
      "text": "Cloro"
    },
    {
      "self_ref": "#/texts/70",
      "parent": {
        "$ref": "#/groups/0"
      },
      "children": [],
      "label": "text",
      "prov": [
        {
          "page_no": 1,
          "bbox": {
            "l": 207.0,
            "t": 347.0,
            "r": 220.33333333333334,
            "b": 341.6666666666667,
            "coord_origin": "BOTTOMLEFT"
          },
          "charspan": [
            0,
            5
          ]
        }
      ],
      "orig": "Flúor",
      "text": "Flúor"
    },
    {
      "self_ref": "#/texts/71",
      "parent": {
        "$ref": "#/groups/0"
      },
      "children": [],
      "label": "text",
      "prov": [
        {
          "page_no": 1,
          "bbox": {
            "l": 229.0,
            "t": 346.3333333333333,
            "r": 268.3333333333333,
            "b": 341.0,
            "coord_origin": "BOTTOMLEFT"
          },
          "charspan": [
            0,
            17
          ]
        }
      ],
      "orig": "Coliformes Totais",
      "text": "Coliformes Totais"
    },
    {
      "self_ref": "#/texts/72",
      "parent": {
        "$ref": "#/groups/0"
      },
      "children": [],
      "label": "text",
      "prov": [
        {
          "page_no": 1,
          "bbox": {
            "l": 277.0,
            "t": 346.3333333333333,
            "r": 306.3333333333333,
            "b": 341.6666666666667,
            "coord_origin": "BOTTOMLEFT"
          },
          "charspan": [
            0,
            16
          ]
        }
      ],
      "orig": "Escherichia Coli",
      "text": "Escherichia Coli"
    },
    {
      "self_ref": "#/texts/73",
      "parent": {
        "$ref": "#/groups/0"
      },
      "children": [],
      "label": "text",
      "prov": [
        {
          "page_no": 1,
          "bbox": {
            "l": 26.666666666666668,
            "t": 338.6666666666667,
            "r": 101.33333333333333,
            "b": 330.6666666666667,
            "coord_origin": "BOTTOMLEFT"
          },
          "charspan": [
            0,
            30
          ]
        }
      ],
      "orig": "N? Mínimo de Amostras Exigidas",
      "text": "N? Mínimo de Amostras Exigidas"
    },
    {
      "self_ref": "#/texts/74",
      "parent": {
        "$ref": "#/groups/0"
      },
      "children": [],
      "label": "text",
      "prov": [
        {
          "page_no": 1,
          "bbox": {
            "l": 32.333333333333336,
            "t": 327.66666666666663,
            "r": 95.0,
            "b": 321.66666666666663,
            "coord_origin": "BOTTOMLEFT"
          },
          "charspan": [
            0,
            25
          ]
        }
      ],
      "orig": "N' de Amostras Analisadas",
      "text": "N' de Amostras Analisadas"
    },
    {
      "self_ref": "#/texts/75",
      "parent": {
        "$ref": "#/groups/0"
      },
      "children": [],
      "label": "text",
      "prov": [
        {
          "page_no": 1,
          "bbox": {
            "l": 17.0,
            "t": 319.0,
            "r": 111.0,
            "b": 314.33333333333337,
            "coord_origin": "BOTTOMLEFT"
          },
          "charspan": [
            0,
            50
          ]
        }
      ],
      "orig": "N' Minimo de Amostras em Conformidade com Portaria",
      "text": "N' Minimo de Amostras em Conformidade com Portaria"
    },
    {
      "self_ref": "#/texts/76",
      "parent": {
        "$ref": "#/groups/0"
      },
      "children": [],
      "label": "text",
      "prov": [
        {
          "page_no": 1,
          "bbox": {
            "l": 57.0,
            "t": 315.0,
            "r": 73.66666666666667,
            "b": 310.33333333333337,
            "coord_origin": "BOTTOMLEFT"
          },
          "charspan": [
            0,
            8
          ]
        }
      ],
      "orig": "914/2011",
      "text": "914/2011"
    },
    {
      "self_ref": "#/texts/77",
      "parent": {
        "$ref": "#/groups/0"
      },
      "children": [],
      "label": "text",
      "prov": [
        {
          "page_no": 1,
          "bbox": {
            "l": 265.6666666666667,
            "t": 304.33333333333337,
            "r": 311.0,
            "b": 299.66666666666663,
            "coord_origin": "BOTTOMLEFT"
          },
          "charspan": [
            0,
            22
          ]
        }
      ],
      "orig": "Favor Aulenticar Verso",
      "text": "Favor Aulenticar Verso"
    },
    {
      "self_ref": "#/texts/78",
      "parent": {
        "$ref": "#/groups/0"
      },
      "children": [],
      "label": "text",
      "prov": [
        {
          "page_no": 1,
          "bbox": {
            "l": 145.0,
            "t": 287.0,
            "r": 195.66666666666666,
            "b": 282.33333333333337,
            "coord_origin": "BOTTOMLEFT"
          },
          "charspan": [
            0,
            19
          ]
        }
      ],
      "orig": "COMPROVANTE DA DESO",
      "text": "COMPROVANTE DA DESO"
    },
    {
      "self_ref": "#/texts/79",
      "parent": {
        "$ref": "#/groups/0"
      },
      "children": [],
      "label": "text",
      "prov": [
        {
          "page_no": 1,
          "bbox": {
            "l": 147.0,
            "t": 280.33333333333337,
            "r": 164.33333333333334,
            "b": 276.33333333333337,
            "coord_origin": "BOTTOMLEFT"
          },
          "charspan": [
            0,
            9
          ]
        }
      ],
      "orig": "Matricula",
      "text": "Matricula"
    },
    {
      "self_ref": "#/texts/80",
      "parent": {
        "$ref": "#/groups/0"
      },
      "children": [],
      "label": "text",
      "prov": [
        {
          "page_no": 1,
          "bbox": {
            "l": 223.66666666666666,
            "t": 281.0,
            "r": 245.66666666666666,
            "b": 276.33333333333337,
            "coord_origin": "BOTTOMLEFT"
          },
          "charspan": [
            0,
            10
          ]
        }
      ],
      "orig": "Vencimento",
      "text": "Vencimento"
    },
    {
      "self_ref": "#/texts/81",
      "parent": {
        "$ref": "#/groups/0"
      },
      "children": [],
      "label": "text",
      "prov": [
        {
          "page_no": 1,
          "bbox": {
            "l": 223.0,
            "t": 262.33333333333337,
            "r": 261.6666666666667,
            "b": 257.66666666666663,
            "coord_origin": "BOTTOMLEFT"
          },
          "charspan": [
            0,
            16
          ]
        }
      ],
      "orig": "TOTAL A PAGAR RS",
      "text": "TOTAL A PAGAR RS"
    },
    {
      "self_ref": "#/texts/82",
      "parent": {
        "$ref": "#/groups/0"
      },
      "children": [],
      "label": "text",
      "prov": [
        {
          "page_no": 1,
          "bbox": {
            "l": 44.333333333333336,
            "t": 259.0,
            "r": 143.0,
            "b": 252.33333333333337,
            "coord_origin": "BOTTOMLEFT"
          },
          "charspan": [
            0,
            34
          ]
        }
      ],
      "orig": "COMPANHIA DE SANEAMENTO DE SERGIPE",
      "text": "COMPANHIA DE SANEAMENTO DE SERGIPE"
    },
    {
      "self_ref": "#/texts/83",
      "parent": {
        "$ref": "#/body"
      },
      "children": [],
      "label": "text",
      "prov": [
        {
          "page_no": 1,
          "bbox": {
            "l": 157.64999389648438,
            "t": 252.875,
            "r": 189.9949951171875,
            "b": 247.3520050048828,
            "coord_origin": "BOTTOMLEFT"
          },
          "charspan": [
            0,
            7
          ]
        }
      ],
      "orig": "02/2024",
      "text": "02/2024"
    },
    {
      "self_ref": "#/texts/84",
      "parent": {
        "$ref": "#/body"
      },
      "children": [],
      "label": "text",
      "prov": [
        {
          "page_no": 1,
          "bbox": {
            "l": 83.05000305175781,
            "t": 243.47500610351562,
            "r": 134.6020050048828,
            "b": 237.95199584960938,
            "coord_origin": "BOTTOMLEFT"
          },
          "charspan": [
            0,
            11
          ]
        }
      ],
      "orig": "119.308.555",
      "text": "119.308.555"
    },
    {
      "self_ref": "#/texts/85",
      "parent": {
        "$ref": "#/body"
      },
      "children": [],
      "label": "text",
      "prov": [
        {
          "page_no": 1,
          "bbox": {
            "l": 278.54998779296875,
            "t": 253.77499389648438,
            "r": 308.4070129394531,
            "b": 248.2519989013672,
            "coord_origin": "BOTTOMLEFT"
          },
          "charspan": [
            0,
            6
          ]
        }
      ],
      "orig": "204,26",
      "text": "204,26"
    },
    {
      "self_ref": "#/texts/86",
      "parent": {
        "$ref": "#/body"
      },
      "children": [],
      "label": "text",
      "prov": [
        {
          "page_no": 1,
          "bbox": {
            "l": 288.0,
            "t": 239.3000030517578,
            "r": 302.20001220703125,
            "b": 235.96800231933594,
            "coord_origin": "BOTTOMLEFT"
          },
          "charspan": [
            0,
            6
          ]
        }
      ],
      "orig": "2ª Via",
      "text": "2ª Via"
    },
    {
      "self_ref": "#/texts/87",
      "parent": {
        "$ref": "#/body"
      },
      "children": [],
      "label": "text",
      "prov": [
        {
          "page_no": 1,
          "bbox": {
            "l": 47.04999923706055,
            "t": 215.625,
            "r": 264.73199462890625,
            "b": 211.21299743652344,
            "coord_origin": "BOTTOMLEFT"
          },
          "charspan": [
            0,
            61
          ]
        }
      ],
      "orig": "82630000002-1   04260041011-4   93085550000-3   50368520012-6",
      "text": "82630000002-1   04260041011-4   93085550000-3   50368520012-6"
    }
  ],
  "pictures": [
    {
      "self_ref": "#/pictures/0",
      "parent": {
        "$ref": "#/body"
      },
      "children": [
        {
          "$ref": "#/texts/0"
        }
      ],
      "label": "picture",
      "prov": [
        {
          "page_no": 1,
          "bbox": {
            "l": 13.103509902954102,
            "t": 833.8076171875,
            "r": 147.9196014404297,
            "b": 794.7577514648438,
            "coord_origin": "BOTTOMLEFT"
          },
          "charspan": [
            0,
            0
          ]
        }
      ],
      "captions": [],
      "references": [],
      "footnotes": [],
      "annotations": []
    },
    {
      "self_ref": "#/pictures/1",
      "parent": {
        "$ref": "#/body"
      },
      "children": [],
      "label": "picture",
      "prov": [
        {
          "page_no": 1,
          "bbox": {
            "l": 9.402100563049316,
            "t": 280.51983642578125,
            "r": 40.74264144897461,
            "b": 252.16815185546875,
            "coord_origin": "BOTTOMLEFT"
          },
          "charspan": [
            0,
            0
          ]
        }
      ],
      "captions": [],
      "references": [],
      "footnotes": [],
      "annotations": []
    },
    {
      "self_ref": "#/pictures/2",
      "parent": {
        "$ref": "#/body"
      },
      "children": [
        {
          "$ref": "#/texts/1"
        }
      ],
      "label": "picture",
      "prov": [
        {
          "page_no": 1,
          "bbox": {
            "l": 43.962886810302734,
            "t": 281.202392578125,
            "r": 142.59730529785156,
            "b": 252.66510009765625,
            "coord_origin": "BOTTOMLEFT"
          },
          "charspan": [
            0,
            0
          ]
        }
      ],
      "captions": [],
      "references": [],
      "footnotes": [],
      "annotations": []
    },
    {
      "self_ref": "#/pictures/3",
      "parent": {
        "$ref": "#/body"
      },
      "children": [],
      "label": "picture",
      "prov": [
        {
          "page_no": 1,
          "bbox": {
            "l": 27.904293060302734,
            "t": 208.95880126953125,
            "r": 279.68389892578125,
            "b": 163.944091796875,
            "coord_origin": "BOTTOMLEFT"
          },
          "charspan": [
            0,
            0
          ]
        }
      ],
      "captions": [],
      "references": [],
      "footnotes": [],
      "annotations": []
    }
  ],
  "tables": [],
  "key_value_items": [],
  "pages": {
    "1": {
      "size": {
        "width": 323.0,
        "height": 842.0
      },
      "page_no": 1
    }
  }
}